Metadata-Version: 1.0
Name: gauss-bin-dist
Version: 0.1
Summary: Gaussian and Binomial distributions
Home-page: UNKNOWN
Author: dmoonat
Author-email: moonatdeepak@gmail.com
License: UNKNOWN
Platform: UNKNOWN
